slurm_top_python/__init__.py
slurm_top_python/constants.py
slurm_top_python/main.py
slurm_top_python/core/__init__.py
slurm_top_python/core/plugin.py
slurm_top_python/interfaces/GUI.py
slurm_top_python/interfaces/__init__.py
slurm_top_python/plugins/__init__.py
slurm_top_python/plugins/cpu_sensor.py
slurm_top_python/plugins/disk_sensor.py
slurm_top_python/plugins/memory_sensor.py
slurm_top_python/plugins/network_sensor.py
slurm_top_python/plugins/process_sensor.py
slurm_top_python/plugins/system_sensor.py
slurm_top_python/statistics/__init__.py
slurm_top_python/statistics/statistics.py
slurm_top_python/utils/__init__.py
slurm_top_python/utils/thread_jobs.py
slurm_top_python-1.0.0a14.dist-info/licenses/LICENSE
slurm_top_python-1.0.0a14.dist-info/licenses/LICENSE-ptop
slurm_top_python-1.0.0a14.dist-info/METADATA
slurm_top_python-1.0.0a14.dist-info/WHEEL
slurm_top_python-1.0.0a14.dist-info/entry_points.txt
slurm_top_python-1.0.0a14.dist-info/top_level.txt
slurm_top_python-1.0.0a14.dist-info/RECORD
