Metadata-Version: 2.4
Name: slurm-top-python
Version: 1.0.0a14
Summary: A task manager written in Python for HPC systems that use Slurm
Author-email: Aashray Reddy <aashrayr.101@gmail.com>
License: The MIT License (MIT)
Project-URL: Homepage, https://github.com/kinetekenergy/slurm_top_python
Project-URL: Issues, https://github.com/kinetekenergy/slurm_top_python
Project-URL: Download, https://github.com/kinetekenergy/slurm_top_python/releases/download/v1.0.0a1/slurm_top_python-1.0.0a1_2025-07-22.tar.gz
Keywords: top,slurm_top_python,task manager,python,slurm,HPC,ptop
Classifier: Development Status :: 3 - Alpha
Classifier: Intended Audience :: Information Technology
Classifier: Natural Language :: English
Classifier: Topic :: System :: Monitoring
Classifier: License :: OSI Approved :: MIT License
Classifier: Programming Language :: Python :: 2
Classifier: Programming Language :: Python :: 2.7
Classifier: Programming Language :: Python :: 3
Classifier: Programming Language :: Python :: 3.3
Classifier: Programming Language :: Python :: 3.4
Classifier: Programming Language :: Python :: 3.5
Classifier: Programming Language :: Python :: 3.6
Classifier: Programming Language :: Python :: 3.7
Requires-Python: >=2.7
License-File: LICENSE
License-File: LICENSE-ptop
Requires-Dist: certifi==2018.10.15
Requires-Dist: chardet==3.0.4
Requires-Dist: drawille==0.1.0
Requires-Dist: idna==2.7
Requires-Dist: lehar==0.4
Requires-Dist: npyscreen==4.10.5
Requires-Dist: psutil==5.6.6
Requires-Dist: requests
Requires-Dist: urllib3
Requires-Dist: argparse==1.4.0
Requires-Dist: huepy==0.9.8.1
Requires-Dist: PyYAML==6.0.2
Dynamic: license-file
